local_determinacy/__init__.py
local_determinacy/functions.py
local_determinacy-0.1.5.dist-info/LICENSE
local_determinacy-0.1.5.dist-info/METADATA
local_determinacy-0.1.5.dist-info/WHEEL
local_determinacy-0.1.5.dist-info/top_level.txt
local_determinacy-0.1.5.dist-info/RECORD
