Metadata-Version: 2.1
Name: local_determinacy
Version: 0.1.5
Summary: A python package for assessing local determinacy in incomplete markets models.
Author-email: Alfred Løvgren <alfred.lovgren@econ.uio.no>, Marcus Hagedorn <marcus.hagedorn@econ.uio.no>
Project-URL: Homepage, https://github.com/alfredlov/local-determinacy/
Project-URL: Issues, https://github.com/alfredlov/local-determinacy/issues
Classifier: Programming Language :: Python :: 3
Classifier: License :: OSI Approved :: MIT License
Classifier: Operating System :: OS Independent
Requires-Python: >=3.8
License-File: LICENSE
